[
  {
    "outageNumber": "1350899",
    "outageStartTime": "1621196160",
    "crewEta": "1621201560",
    "crewCurrentStatus": "PG&E repair crew is on-site working to restore power.",
    "currentEtor": "1621267200",
    "cause": "Our preliminary determination is that your outage was caused by an equipment issue.",
    "estCustAffected": "144",
    "lastUpdateTime": "1621228694",
    "hazardFlag": "1",
    "latitude": "37.99858",
    "longitude": "-121.78302",
    "outageDevices": [
      {
        "latitude": "37.96953",
        "longitude": "-121.77914"
      },
      {
        "latitude": "37.96954",
        "longitude": "-121.77727"
      },
      {
        "latitude": "37.9713",
        "longitude": "-121.77787"
      },
      {
        "latitude": "37.9716",
        "longitude": "-121.77969"
      },
      {
        "latitude": "37.97141",
        "longitude": "-121.78099"
      },
      {
        "latitude": "37.97083",
        "longitude": "-121.78086"
      },
      {
        "latitude": "37.97019",
        "longitude": "-121.78022"
      }
    ],
    "regionName": "Antioch"
  },
  {
    "outageNumber": "1351043",
    "outageStartTime": "1621226049",
    "crewCurrentStatus": "PG&E repair crew is on-site working to restore power.",
    "currentEtor": "1621267200",
    "cause": "Our preliminary determination is that your outage was caused by an equipment issue.",
    "estCustAffected": "40",
    "lastUpdateTime": "1621229299",
    "hazardFlag": "0",
    "latitude": "37.9633",
    "longitude": "-121.78044",
    "outageDevices": [
      {
        "latitude": "37.94772",
        "longitude": "-121.76755"
      },
      {
        "latitude": "37.9656",
        "longitude": "-121.77117"
      },
      {
        "latitude": "37.96627",
        "longitude": "-121.7738"
      },
      {
        "latitude": "37.96471",
        "longitude": "-121.78073"
      },
      {
        "latitude": "37.9496",
        "longitude": "-121.77766"
      }
    ],
    "regionName": "Antioch"
  },
  {
    "outageNumber": "1351078",
    "outageStartTime": "1621239560",
    "crewCurrentStatus": "PG&E is assessing the cause at the outage location.",
    "autoEtor": "1621252800",
    "currentEtor": "1621252800",
    "cause": "PG&E is investigating the cause of your outage.",
    "estCustAffected": "1",
    "lastUpdateTime": "1621241212",
    "hazardFlag": "1",
    "latitude": "35.43607",
    "longitude": "-119.11958",
    "regionName": "Bakersfield"
  },
  {
    "outageNumber": "1350952",
    "outageStartTime": "1621206060",
    "crewCurrentStatus": "PG&E is sending a repair crew to the outage location.",
    "currentEtor": "1621263600",
    "cause": "Our preliminary determination is that your outage was caused by an equipment issue.",
    "estCustAffected": "10",
    "lastUpdateTime": "1621239385",
    "hazardFlag": "1",
    "latitude": "35.41087",
    "longitude": "-118.95865",
    "regionName": "Bakersfield"
  },
  {
    "outageNumber": "1349836",
    "outageStartTime": "1621089540",
    "crewCurrentStatus": "PG&E repair crew is on-site working to restore power.",
    "currentEtor": "1621130400",
    "cause": "Our preliminary determination is that your outage was caused by scheduled maintenance work.",
    "estCustAffected": "2",
    "lastUpdateTime": "1621089847",
    "hazardFlag": "0",
    "latitude": "39.70997",
    "longitude": "-121.813",
    "regionName": "Chico"
  },
  {
    "outageNumber": "1350839",
    "outageStartTime": "1621187700",
    "crewCurrentStatus": "PG&E is sending a repair crew to the outage location.",
    "currentEtor": "1621263600",
    "cause": "Our preliminary determination is that your outage was caused by a car that hit a pole.",
    "estCustAffected": "4",
    "lastUpdateTime": "1621223649",
    "hazardFlag": "2",
    "latitude": "36.82627",
    "longitude": "-119.68104",
    "regionName": "Clovis"
  },
  {
    "outageNumber": "1350549",
    "outageStartTime": "1621127732",
    "crewCurrentStatus": "PG&E has assigned a crew to assess the outage.",
    "currentEtor": "1621278000",
    "cause": "Unknown - PG&E will be assessing the cause.",
    "estCustAffected": "1",
    "lastUpdateTime": "1621149337",
    "hazardFlag": "0",
    "latitude": "36.58369",
    "longitude": "-119.71752",
    "regionName": "Fowler"
  },
  {
    "outageNumber": "1350838",
    "outageStartTime": "1621187760",
    "crewEta": "1621225320",
    "crewCurrentStatus": "PG&E repair crew is on-site working to restore power.",
    "currentEtor": "1621270800",
    "cause": "Our preliminary determination is that your outage was caused by a car that hit a pole.",
    "estCustAffected": "23",
    "lastUpdateTime": "1621225142",
    "hazardFlag": "0",
    "latitude": "36.77813",
    "longitude": "-119.67409",
    "outageDevices": [
      {
        "latitude": "36.81951",
        "longitude": "-119.64608"
      },
      {
        "latitude": "36.82098",
        "longitude": "-119.64187"
      },
      {
        "latitude": "36.82119",
        "longitude": "-119.64597"
      },
      {
        "latitude": "36.8199",
        "longitude": "-119.64706"
      }
    ],
    "regionName": "Fresno"
  },
  {
    "outageNumber": "1351055",
    "outageStartTime": "1621234690",
    "crewEta": "1621241340",
    "crewCurrentStatus": "PG&E is assessing the cause at the outage location.",
    "autoEtor": "1621244700",
    "currentEtor": "1621244700",
    "cause": "PG&E is investigating the cause of your outage.",
    "estCustAffected": "27",
    "lastUpdateTime": "1621241459",
    "hazardFlag": "1",
    "latitude": "36.77497",
    "longitude": "-119.73643",
    "outageDevices": [
      {
        "latitude": "36.77484",
        "longitude": "-119.73216"
      },
      {
        "latitude": "36.77491",
        "longitude": "-119.73348"
      },
      {
        "latitude": "36.77492",
        "longitude": "-119.73521"
      },
      {
        "latitude": "36.77484",
        "longitude": "-119.73272"
      }
    ],
    "regionName": "Fresno"
  },
  {
    "outageNumber": "1350936",
    "outageStartTime": "1621202160",
    "crewEta": "1621235220",
    "crewCurrentStatus": "PG&E repair crew is on-site working to restore power.",
    "currentEtor": "1621260000",
    "cause": "Our preliminary determination is that your outage was caused by an equipment issue.",
    "estCustAffected": "26",
    "lastUpdateTime": "1621234087",
    "hazardFlag": "0",
    "latitude": "36.77214",
    "longitude": "-119.77641",
    "regionName": "Fresno"
  },
  {
    "outageNumber": "1351070",
    "outageStartTime": "1621236776",
    "crewCurrentStatus": "PG&E is sending a repair crew to the outage location.",
    "autoEtor": "1621246500",
    "currentEtor": "1621246500",
    "cause": "Our preliminary determination is that your outage was caused by an equipment issue.",
    "estCustAffected": "1",
    "lastUpdateTime": "1621237965",
    "hazardFlag": "1",
    "latitude": "36.73328",
    "longitude": "-119.75714",
    "regionName": "Fresno"
  },
  {
    "outageNumber": "1351047",
    "outageStartTime": "1621230100",
    "crewCurrentStatus": "PG&E is assessing the cause at the outage location.",
    "currentEtor": "1621247460",
    "cause": "PG&E is investigating the cause of your outage.",
    "estCustAffected": "32",
    "lastUpdateTime": "1621240335",
    "hazardFlag": "0",
    "latitude": "37.66464",
    "longitude": "-122.02798",
    "outageDevices": [
      {
        "latitude": "37.66281",
        "longitude": "-122.02979"
      },
      {
        "latitude": "37.66311",
        "longitude": "-122.02831"
      },
      {
        "latitude": "37.66445",
        "longitude": "-122.02846"
      },
      {
        "latitude": "37.66588",
        "longitude": "-122.02884"
      },
      {
        "latitude": "37.66583",
        "longitude": "-122.02993"
      },
      {
        "latitude": "37.66504",
        "longitude": "-122.03036"
      }
    ],
    "regionName": "Hayward"
  },
  {
    "outageNumber": "1351050",
    "outageStartTime": "1621232385",
    "crewCurrentStatus": "PG&E repair crew is on-site working to restore power.",
    "autoEtor": "1621245600",
    "currentEtor": "1621245600",
    "cause": "Our preliminary determination is that your outage was caused by a car that hit a pole.",
    "estCustAffected": "4",
    "lastUpdateTime": "1621236750",
    "hazardFlag": "1",
    "latitude": "35.26702",
    "longitude": "-118.91945",
    "regionName": "Lamont"
  },
  {
    "outageNumber": "1351031",
    "outageStartTime": "1621221491",
    "crewCurrentStatus": "PG&E repair crew is en route to the outage location.",
    "currentEtor": "1621245600",
    "cause": "Our preliminary determination is that your outage was caused by an equipment issue.",
    "estCustAffected": "1",
    "lastUpdateTime": "1621227936",
    "hazardFlag": "0",
    "latitude": "38.03385",
    "longitude": "-122.54251",
    "regionName": "Lucas Valley-Marinwood"
  },
  {
    "outageNumber": "1351075",
    "outageStartTime": "1621238485",
    "crewCurrentStatus": "PG&E has assigned a crew to assess the outage.",
    "autoEtor": "1621251900",
    "currentEtor": "1621251900",
    "cause": "Unknown - PG&E will be assessing the cause.",
    "estCustAffected": "1",
    "lastUpdateTime": "1621239892",
    "hazardFlag": "0",
    "latitude": "38.03385",
    "longitude": "-122.54251",
    "regionName": "Lucas Valley-Marinwood"
  },
  {
    "outageNumber": "1351048",
    "outageStartTime": "1621230240",
    "crewCurrentStatus": "PG&E is assessing the cause at the outage location.",
    "currentEtor": "1621260000",
    "cause": "PG&E is investigating the cause of your outage.",
    "estCustAffected": "77",
    "lastUpdateTime": "1621241292",
    "hazardFlag": "0",
    "latitude": "38.04427",
    "longitude": "-122.61547",
    "outageDevices": [
      {
        "latitude": "38.03294",
        "longitude": "-122.6482"
      },
      {
        "latitude": "38.03378",
        "longitude": "-122.64581"
      },
      {
        "latitude": "38.035",
        "longitude": "-122.6427"
      },
      {
        "latitude": "38.03521",
        "longitude": "-122.64219"
      },
      {
        "latitude": "38.04862",
        "longitude": "-122.62573"
      },
      {
        "latitude": "38.05667",
        "longitude": "-122.65665"
      },
      {
        "latitude": "38.03957",
        "longitude": "-122.65799"
      }
    ],
    "regionName": "Lucas Valley-Marinwood"
  },
  {
    "outageNumber": "1351074",
    "outageStartTime": "1621238395",
    "crewCurrentStatus": "PG&E has assigned a crew to assess the outage.",
    "currentEtor": "1621422000",
    "cause": "Our preliminary determination is that your outage was caused by scheduled maintenance work.",
    "estCustAffected": "26",
    "lastUpdateTime": "1621238783",
    "hazardFlag": "0",
    "latitude": "38.24664",
    "longitude": "-122.27387",
    "outageDevices": [
      {
        "latitude": "38.24534",
        "longitude": "-122.27619"
      },
      {
        "latitude": "38.24574",
        "longitude": "-122.27302"
      },
      {
        "latitude": "38.24582",
        "longitude": "-122.27277"
      },
      {
        "latitude": "38.24929",
        "longitude": "-122.27448"
      },
      {
        "latitude": "38.24883",
        "longitude": "-122.27762"
      },
      {
        "latitude": "38.24774",
        "longitude": "-122.2791"
      },
      {
        "latitude": "38.24537",
        "longitude": "-122.27883"
      }
    ],
    "regionName": "Napa"
  },
  {
    "outageNumber": "1351056",
    "outageStartTime": "1621234848",
    "crewEta": "1621240380",
    "crewCurrentStatus": "PG&E is assessing the cause at the outage location.",
    "autoEtor": "1621246500",
    "currentEtor": "1621246500",
    "cause": "PG&E is investigating the cause of your outage.",
    "estCustAffected": "1",
    "lastUpdateTime": "1621239869",
    "hazardFlag": "0",
    "latitude": "39.19027",
    "longitude": "-121.2014",
    "regionName": "Penn Valley"
  },
  {
    "outageNumber": "1351071",
    "outageStartTime": "1621237106",
    "crewEta": "1621241640",
    "crewCurrentStatus": "PG&E is assessing the cause at the outage location.",
    "autoEtor": "1621250100",
    "currentEtor": "1621250100",
    "cause": "PG&E is investigating the cause of your outage.",
    "estCustAffected": "156",
    "lastUpdateTime": "1621240110",
    "hazardFlag": "2",
    "latitude": "36.74927",
    "longitude": "-121.65733",
    "outageDevices": [
      {
        "latitude": "36.74982",
        "longitude": "-121.65714"
      },
      {
        "latitude": "36.75865",
        "longitude": "-121.64601"
      },
      {
        "latitude": "36.77077",
        "longitude": "-121.64867"
      },
      {
        "latitude": "36.76506",
        "longitude": "-121.66455"
      },
      {
        "latitude": "36.76453",
        "longitude": "-121.66558"
      }
    ],
    "regionName": "Salinas"
  },
  {
    "outageNumber": "1351049",
    "outageStartTime": "1621230891",
    "crewCurrentStatus": "PG&E repair crew is on-site working to restore power.",
    "currentEtor": "1621249200",
    "cause": "Our preliminary determination is that your outage was caused by an equipment issue.",
    "estCustAffected": "50",
    "lastUpdateTime": "1621238768",
    "hazardFlag": "1",
    "latitude": "36.73572",
    "longitude": "-121.75968",
    "outageDevices": [
      {
        "latitude": "36.70761",
        "longitude": "-121.74695"
      },
      {
        "latitude": "36.71081",
        "longitude": "-121.73955"
      },
      {
        "latitude": "36.71108",
        "longitude": "-121.73895"
      },
      {
        "latitude": "36.72163",
        "longitude": "-121.73764"
      },
      {
        "latitude": "36.73462",
        "longitude": "-121.73773"
      },
      {
        "latitude": "36.7384",
        "longitude": "-121.75168"
      },
      {
        "latitude": "36.73513",
        "longitude": "-121.75963"
      },
      {
        "latitude": "36.72515",
        "longitude": "-121.7606"
      },
      {
        "latitude": "36.71981",
        "longitude": "-121.75701"
      }
    ],
    "regionName": "Salinas"
  },
  {
    "outageNumber": "1351073",
    "outageStartTime": "1621237500",
    "crewEta": "1621240320",
    "crewCurrentStatus": "PG&E is assessing the cause at the outage location.",
    "autoEtor": "1621250100",
    "currentEtor": "1621250100",
    "cause": "PG&E is investigating the cause of your outage.",
    "estCustAffected": "180",
    "lastUpdateTime": "1621241106",
    "hazardFlag": "0",
    "latitude": "37.34906",
    "longitude": "-121.8469",
    "outageDevices": [
      {
        "latitude": "37.34864",
        "longitude": "-121.84917"
      },
      {
        "latitude": "37.34968",
        "longitude": "-121.84754"
      },
      {
        "latitude": "37.35046",
        "longitude": "-121.84813"
      },
      {
        "latitude": "37.3508",
        "longitude": "-121.84839"
      },
      {
        "latitude": "37.35047",
        "longitude": "-121.84956"
      },
      {
        "latitude": "37.35007",
        "longitude": "-121.85029"
      },
      {
        "latitude": "37.34925",
        "longitude": "-121.851"
      },
      {
        "latitude": "37.34873",
        "longitude": "-121.84965"
      }
    ],
    "regionName": "San Jose"
  },
  {
    "outageNumber": "1351082",
    "outageStartTime": "1621241040",
    "crewCurrentStatus": "PG&E has assigned a crew to assess the outage.",
    "autoEtor": "1621251000",
    "currentEtor": "1621251000",
    "cause": "Unknown - PG&E will be assessing the cause.",
    "estCustAffected": "1",
    "lastUpdateTime": "1621241364",
    "hazardFlag": "0",
    "latitude": "37.55167",
    "longitude": "-122.32604",
    "regionName": "San Mateo"
  },
  {
    "outageNumber": "1351077",
    "outageStartTime": "1621239498",
    "crewCurrentStatus": "PG&E has assigned a crew to assess the outage.",
    "autoEtor": "1621249200",
    "currentEtor": "1621249200",
    "cause": "Unknown - PG&E will be assessing the cause.",
    "estCustAffected": "78",
    "lastUpdateTime": "1621240216",
    "hazardFlag": "0",
    "latitude": "37.55668",
    "longitude": "-122.32405",
    "outageDevices": [
      {
        "latitude": "37.55252",
        "longitude": "-122.32897"
      },
      {
        "latitude": "37.55342",
        "longitude": "-122.3279"
      },
      {
        "latitude": "37.5561",
        "longitude": "-122.32475"
      },
      {
        "latitude": "37.55645",
        "longitude": "-122.32434"
      },
      {
        "latitude": "37.55432",
        "longitude": "-122.32686"
      }
    ],
    "regionName": "San Mateo"
  },
  {
    "outageNumber": "1351076",
    "outageStartTime": "1621239300",
    "crewCurrentStatus": "PG&E has assigned a crew to assess the outage.",
    "autoEtor": "1621253700",
    "currentEtor": "1621253700",
    "cause": "Unknown - PG&E will be assessing the cause.",
    "estCustAffected": "1",
    "lastUpdateTime": "1621240720",
    "hazardFlag": "0",
    "latitude": "36.9743",
    "longitude": "-122.03013",
    "regionName": "Santa Cruz"
  },
  {
    "outageNumber": "1351052",
    "outageStartTime": "1621234316",
    "crewCurrentStatus": "PG&E has assigned a crew to assess the outage.",
    "autoEtor": "1621245600",
    "currentEtor": "1621245600",
    "cause": "Unknown - PG&E will be assessing the cause.",
    "estCustAffected": "1",
    "lastUpdateTime": "1621234856",
    "hazardFlag": "0",
    "latitude": "36.60648",
    "longitude": "-121.85654",
    "regionName": "Seaside"
  },
  {
    "outageNumber": "1345878",
    "outageStartTime": "1620750691",
    "crewEta": "1620751140",
    "crewCurrentStatus": "PG&E repair crew is on-site working to restore power.",
    "currentEtor": "1621641600",
    "cause": "Our preliminary determination is that your outage was caused by scheduled maintenance work.",
    "estCustAffected": "1",
    "lastUpdateTime": "1620752403",
    "hazardFlag": "0",
    "latitude": "37.35875",
    "longitude": "-122.0216",
    "regionName": "Sunnyvale"
  },
  {
    "outageNumber": "1351051",
    "outageStartTime": "1621232580",
    "crewEta": "1621237560",
    "crewCurrentStatus": "PG&E is assessing the cause at the outage location.",
    "autoEtor": "1621243800",
    "currentEtor": "1621243800",
    "cause": "PG&E is investigating the cause of your outage.",
    "estCustAffected": "6",
    "lastUpdateTime": "1621239437",
    "hazardFlag": "2",
    "latitude": "37.78127",
    "longitude": "-121.46355",
    "outageDevices": [
      {
        "latitude": "37.78315",
        "longitude": "-121.46241"
      },
      {
        "latitude": "37.78316",
        "longitude": "-121.45728"
      },
      {
        "latitude": "37.78316",
        "longitude": "-121.46052"
      }
    ],
    "regionName": "Tracy"
  },
  {
    "outageNumber": "1351059",
    "outageStartTime": "1621234500",
    "crewCurrentStatus": "PG&E has assigned a crew to assess the outage.",
    "cause": "Our preliminary determination is that your outage was caused by the weather.",
    "estCustAffected": "50",
    "lastUpdateTime": "1621235139",
    "hazardFlag": "0",
    "latitude": "40.92181",
    "longitude": "-123.62305",
    "outageDevices": [
      {
        "latitude": "40.92042",
        "longitude": "-123.62141"
      },
      {
        "latitude": "40.92061",
        "longitude": "-123.61675"
      },
      {
        "latitude": "40.92103",
        "longitude": "-123.61631"
      },
      {
        "latitude": "40.92158",
        "longitude": "-123.61574"
      },
      {
        "latitude": "40.92269",
        "longitude": "-123.61668"
      },
      {
        "latitude": "40.92466",
        "longitude": "-123.62115"
      },
      {
        "latitude": "40.92421",
        "longitude": "-123.62153"
      },
      {
        "latitude": "40.92147",
        "longitude": "-123.62234"
      }
    ],
    "regionName": "Willow Creek"
  }
]