[
  {
    "outageNumber": "1199492",
    "outageStartTime": "1609102418",
    "crewCurrentStatus": "PG&E assessment crew is en route to the outage.",
    "autoEtor": "1609113600",
    "currentEtor": "1609113600",
    "cause": "Unknown - PG&E will be assessing the cause.",
    "estCustAffected": "33",
    "lastUpdateTime": "1609103041",
    "hazardFlag": "3",
    "latitude": "35.33113",
    "longitude": "-119.07469",
    "outageDevices": [
      {
        "latitude": "35.33046",
        "longitude": "-119.07504"
      },
      {
        "latitude": "35.33153",
        "longitude": "-119.0749"
      },
      {
        "latitude": "35.33124",
        "longitude": "-119.07508"
      }
    ],
    "regionName": "Bakersfield"
  },
  {
    "outageNumber": "1199497",
    "outageStartTime": "1609102699",
    "crewCurrentStatus": "PG&E has assigned a crew to assess the outage.",
    "autoEtor": "1609113600",
    "currentEtor": "1609113600",
    "cause": "Unknown - PG&E will be assessing the cause.",
    "estCustAffected": "1",
    "lastUpdateTime": "1609103114",
    "hazardFlag": "2",
    "latitude": "38.00445",
    "longitude": "-122.31939",
    "regionName": "Bayview-Montalvin"
  },
  {
    "outageNumber": "1199487",
    "outageStartTime": "1609101876",
    "crewCurrentStatus": "PG&E has assigned a crew to assess the outage.",
    "autoEtor": "1609115400",
    "currentEtor": "1609115400",
    "cause": "Unknown - PG&E will be assessing the cause.",
    "estCustAffected": "1",
    "lastUpdateTime": "1609102177",
    "hazardFlag": "0",
    "latitude": "38.33286",
    "longitude": "-123.04632",
    "regionName": "Bodega Bay"
  },
  {
    "outageNumber": "1199488",
    "outageStartTime": "1609101876",
    "crewEta": "1609105680",
    "crewCurrentStatus": "PG&E assessment crew is en route to the outage.",
    "autoEtor": "1609115400",
    "currentEtor": "1609115400",
    "cause": "Unknown - PG&E will be assessing the cause.",
    "estCustAffected": "41",
    "lastUpdateTime": "1609102377",
    "hazardFlag": "0",
    "latitude": "38.33297",
    "longitude": "-123.0471",
    "outageDevices": [
      {
        "latitude": "38.33258",
        "longitude": "-123.0467"
      },
      {
        "latitude": "38.33415",
        "longitude": "-123.0477"
      },
      {
        "latitude": "38.33459",
        "longitude": "-123.0482"
      },
      {
        "latitude": "38.33329",
        "longitude": "-123.04725"
      }
    ],
    "regionName": "Bodega Bay"
  },
  {
    "outageNumber": "1199388",
    "outageStartTime": "1609087372",
    "crewCurrentStatus": "PG&E has assigned a crew to assess the outage.",
    "currentEtor": "1609110900",
    "cause": "Unknown - PG&E will be assessing the cause.",
    "estCustAffected": "1",
    "lastUpdateTime": "1609098745",
    "hazardFlag": "1",
    "latitude": "40.53436",
    "longitude": "-124.03841",
    "regionName": "Carlotta"
  },
  {
    "outageNumber": "1199482",
    "outageStartTime": "1609100220",
    "crewEta": "1609102380",
    "crewCurrentStatus": "PG&E is assessing the cause at the outage location.",
    "autoEtor": "1609111800",
    "currentEtor": "1609111800",
    "cause": "PG&E is investigating the cause of your outage.",
    "estCustAffected": "93",
    "lastUpdateTime": "1609102367",
    "hazardFlag": "2",
    "latitude": "36.55642",
    "longitude": "-121.90872",
    "outageDevices": [
      {
        "latitude": "36.55661",
        "longitude": "-121.90884"
      },
      {
        "latitude": "36.55708",
        "longitude": "-121.90754"
      },
      {
        "latitude": "36.56524",
        "longitude": "-121.91249"
      },
      {
        "latitude": "36.55697",
        "longitude": "-121.91094"
      }
    ],
    "regionName": "Carmel"
  },
  {
    "outageNumber": "1199346",
    "outageStartTime": "1609055880",
    "crewCurrentStatus": "PG&E repair crew is on-site working to restore power.",
    "currentEtor": "1609117200",
    "cause": "Our preliminary determination is that your outage was caused by an emergency issue.",
    "estCustAffected": "480",
    "lastUpdateTime": "1609098483",
    "hazardFlag": "2",
    "latitude": "37.70254",
    "longitude": "-122.11028",
    "outageDevices": [
      {
        "latitude": "37.70261",
        "longitude": "-122.11024"
      },
      {
        "latitude": "37.70423",
        "longitude": "-122.10835"
      },
      {
        "latitude": "37.70492",
        "longitude": "-122.10762"
      },
      {
        "latitude": "37.70533",
        "longitude": "-122.10741"
      },
      {
        "latitude": "37.70785",
        "longitude": "-122.10931"
      },
      {
        "latitude": "37.7085",
        "longitude": "-122.11182"
      },
      {
        "latitude": "37.70861",
        "longitude": "-122.1124"
      },
      {
        "latitude": "37.70619",
        "longitude": "-122.11634"
      },
      {
        "latitude": "37.70575",
        "longitude": "-122.11586"
      }
    ],
    "regionName": "Castro Valley"
  },
  {
    "outageNumber": "1199377",
    "outageStartTime": "1609082701",
    "crewCurrentStatus": "PG&E is sending a repair crew to the outage location.",
    "currentEtor": "1609110000",
    "cause": "Our preliminary determination is that your outage was caused by an equipment issue.",
    "estCustAffected": "4",
    "lastUpdateTime": "1609102153",
    "hazardFlag": "0",
    "latitude": "38.27605",
    "longitude": "-121.59182",
    "regionName": "Courtland"
  },
  {
    "outageNumber": "1199446",
    "outageStartTime": "1609095024",
    "crewCurrentStatus": "PG&E assessment crew is en route to the outage.",
    "autoEtor": "1609109100",
    "currentEtor": "1609109100",
    "cause": "Unknown - PG&E will be assessing the cause.",
    "estCustAffected": "1",
    "lastUpdateTime": "1609095035",
    "hazardFlag": "0",
    "latitude": "37.47332",
    "longitude": "-122.27666",
    "regionName": "Emerald Lake Hills"
  },
  {
    "outageNumber": "1197008",
    "outageStartTime": "1608652800",
    "crewCurrentStatus": "PG&E repair crew is on-site working to restore power.",
    "currentEtor": "1609272000",
    "cause": "Our preliminary determination is that your outage was caused by scheduled maintenance work.",
    "estCustAffected": "1",
    "lastUpdateTime": "1608664187",
    "hazardFlag": "0",
    "latitude": "38.29748",
    "longitude": "-121.96713",
    "regionName": "Fairfield"
  },
  {
    "outageNumber": "1199419",
    "outageStartTime": "1609092002",
    "crewEta": "1609100160",
    "crewCurrentStatus": "PG&E repair crew is on-site working to restore power.",
    "currentEtor": "1609117200",
    "cause": "Our preliminary determination is that your outage was caused by an equipment issue.",
    "estCustAffected": "54",
    "lastUpdateTime": "1609103411",
    "hazardFlag": "2",
    "latitude": "40.59115",
    "longitude": "-124.14464",
    "regionName": "Fortuna"
  },
  {
    "outageNumber": "1199405",
    "outageStartTime": "1609089900",
    "crewCurrentStatus": "PG&E assessment crew is en route to the outage.",
    "currentEtor": "1609108200",
    "cause": "Unknown - PG&E will be assessing the cause.",
    "estCustAffected": "1",
    "lastUpdateTime": "1609098429",
    "hazardFlag": "0",
    "latitude": "40.58503",
    "longitude": "-124.14692",
    "regionName": "Fortuna"
  },
  {
    "outageNumber": "1199480",
    "outageStartTime": "1609100187",
    "crewCurrentStatus": "PG&E is assessing the cause at the outage location.",
    "autoEtor": "1609110000",
    "currentEtor": "1609110000",
    "cause": "PG&E is investigating the cause of your outage.",
    "estCustAffected": "19",
    "lastUpdateTime": "1609103214",
    "hazardFlag": "2",
    "latitude": "36.78452",
    "longitude": "-119.83598",
    "regionName": "Fresno"
  },
  {
    "outageNumber": "1199474",
    "outageStartTime": "1609099470",
    "crewCurrentStatus": "PG&E has assigned a crew to assess the outage.",
    "autoEtor": "1609111800",
    "currentEtor": "1609111800",
    "cause": "Unknown - PG&E will be assessing the cause.",
    "estCustAffected": "1",
    "lastUpdateTime": "1609100108",
    "hazardFlag": "1",
    "latitude": "37.01583",
    "longitude": "-121.58173",
    "regionName": "Gilroy"
  },
  {
    "outageNumber": "1199463",
    "outageStartTime": "1609098753",
    "crewEta": "1609100760",
    "crewCurrentStatus": "PG&E is assessing the cause at the outage location.",
    "autoEtor": "1609110900",
    "currentEtor": "1609110900",
    "cause": "PG&E is investigating the cause of your outage.",
    "estCustAffected": "9",
    "lastUpdateTime": "1609102680",
    "hazardFlag": "1",
    "latitude": "36.99435",
    "longitude": "-121.55876",
    "regionName": "Gilroy"
  },
  {
    "outageNumber": "1199476",
    "outageStartTime": "1609099505",
    "crewEta": "1609103760",
    "crewCurrentStatus": "PG&E is assessing the cause at the outage location.",
    "autoEtor": "1609110900",
    "currentEtor": "1609110900",
    "cause": "Our preliminary determination is that your outage was caused by an equipment issue.",
    "estCustAffected": "55",
    "lastUpdateTime": "1609103744",
    "hazardFlag": "0",
    "latitude": "36.51815",
    "longitude": "-121.4601",
    "outageDevices": [
      {
        "latitude": "36.48958",
        "longitude": "-121.47326"
      },
      {
        "latitude": "36.49199",
        "longitude": "-121.4713"
      },
      {
        "latitude": "36.49242",
        "longitude": "-121.47096"
      },
      {
        "latitude": "36.51802",
        "longitude": "-121.46032"
      },
      {
        "latitude": "36.51833",
        "longitude": "-121.47659"
      },
      {
        "latitude": "36.51674",
        "longitude": "-121.48495"
      },
      {
        "latitude": "36.51547",
        "longitude": "-121.49161"
      },
      {
        "latitude": "36.49633",
        "longitude": "-121.48565"
      }
    ],
    "regionName": "Gonzales"
  },
  {
    "outageNumber": "1199479",
    "outageStartTime": "1609099895",
    "crewEta": "1609103880",
    "crewCurrentStatus": "PG&E is assessing the cause at the outage location.",
    "autoEtor": "1609111800",
    "currentEtor": "1609111800",
    "cause": "PG&E is investigating the cause of your outage.",
    "estCustAffected": "15",
    "lastUpdateTime": "1609103798",
    "hazardFlag": "0",
    "latitude": "39.22108",
    "longitude": "-121.01395",
    "regionName": "Grass Valley"
  },
  {
    "outageNumber": "1199486",
    "outageStartTime": "1609101416",
    "crewCurrentStatus": "PG&E assessment crew is en route to the outage.",
    "autoEtor": "1609111800",
    "currentEtor": "1609111800",
    "cause": "Unknown - PG&E will be assessing the cause.",
    "estCustAffected": "1",
    "lastUpdateTime": "1609101522",
    "hazardFlag": "0",
    "latitude": "38.00712",
    "longitude": "-122.27822",
    "regionName": "Hercules"
  },
  {
    "outageNumber": "1199400",
    "outageStartTime": "1609088931",
    "crewEta": "1609106400",
    "crewCurrentStatus": "PG&E repair crew is en route to the outage location.",
    "currentEtor": "1609128000",
    "cause": "Our preliminary determination is that your outage was caused by an equipment issue.",
    "estCustAffected": "5",
    "lastUpdateTime": "1609100877",
    "hazardFlag": "0",
    "latitude": "36.64772",
    "longitude": "-120.16725",
    "regionName": "Kerman"
  },
  {
    "outageNumber": "1199352",
    "outageStartTime": "1609051740",
    "crewCurrentStatus": "PG&E repair crew is on-site working to restore power.",
    "currentEtor": "1609106400",
    "cause": "Our preliminary determination is that your outage was caused by a car that hit a pole.",
    "estCustAffected": "48",
    "lastUpdateTime": "1609101625",
    "hazardFlag": "0",
    "latitude": "39.03659",
    "longitude": "-121.07632",
    "outageDevices": [
      {
        "latitude": "39.02874",
        "longitude": "-121.07561"
      },
      {
        "latitude": "39.0338",
        "longitude": "-121.07651"
      },
      {
        "latitude": "39.03422",
        "longitude": "-121.07667"
      },
      {
        "latitude": "39.03834",
        "longitude": "-121.07844"
      },
      {
        "latitude": "39.03923",
        "longitude": "-121.07901"
      },
      {
        "latitude": "39.03274",
        "longitude": "-121.08665"
      },
      {
        "latitude": "39.03156",
        "longitude": "-121.0853"
      },
      {
        "latitude": "39.02946",
        "longitude": "-121.07998"
      }
    ],
    "regionName": "Lake of the Pines"
  },
  {
    "outageNumber": "1199483",
    "outageStartTime": "1609100040",
    "crewEta": "1609106460",
    "crewCurrentStatus": "PG&E assessment crew is en route to the outage.",
    "autoEtor": "1609110900",
    "currentEtor": "1609110900",
    "cause": "Unknown - PG&E will be assessing the cause.",
    "estCustAffected": "1",
    "lastUpdateTime": "1609101331",
    "hazardFlag": "0",
    "latitude": "36.95446",
    "longitude": "-120.80479",
    "regionName": "Los Banos"
  },
  {
    "outageNumber": "1199473",
    "outageStartTime": "1609099320",
    "crewCurrentStatus": "PG&E assessment crew is en route to the outage.",
    "autoEtor": "1609116300",
    "currentEtor": "1609116300",
    "cause": "Unknown - PG&E will be assessing the cause.",
    "estCustAffected": "3",
    "lastUpdateTime": "1609100998",
    "hazardFlag": "0",
    "latitude": "34.94892",
    "longitude": "-119.8176",
    "regionName": "New Cuyama"
  },
  {
    "outageNumber": "1199485",
    "outageStartTime": "1609101318",
    "crewCurrentStatus": "PG&E is assessing the cause at the outage location.",
    "autoEtor": "1609110900",
    "currentEtor": "1609110900",
    "cause": "PG&E is investigating the cause of your outage.",
    "estCustAffected": "1",
    "lastUpdateTime": "1609102182",
    "hazardFlag": "0",
    "latitude": "37.79431",
    "longitude": "-122.26791",
    "regionName": "Oakland"
  },
  {
    "outageNumber": "1199387",
    "outageStartTime": "1609087093",
    "crewCurrentStatus": "PG&E is sending a repair crew to the outage location.",
    "currentEtor": "1609120800",
    "cause": "Our preliminary determination is that your outage was caused by an equipment issue.",
    "estCustAffected": "1",
    "lastUpdateTime": "1609098155",
    "hazardFlag": "0",
    "latitude": "37.82185",
    "longitude": "-122.24985",
    "regionName": "Oakland"
  },
  {
    "outageNumber": "1199449",
    "outageStartTime": "1609095743",
    "crewCurrentStatus": "PG&E is sending a repair crew to the outage location.",
    "autoEtor": "1609114500",
    "currentEtor": "1609114500",
    "cause": "PG&E is investigating the cause of your outage.",
    "estCustAffected": "4",
    "lastUpdateTime": "1609100147",
    "hazardFlag": "0",
    "latitude": "35.43515",
    "longitude": "-119.01444",
    "regionName": "Oildale"
  },
  {
    "outageNumber": "1199448",
    "outageStartTime": "1609095739",
    "crewCurrentStatus": "PG&E is sending a repair crew to the outage location.",
    "autoEtor": "1609114500",
    "currentEtor": "1609114500",
    "cause": "PG&E is investigating the cause of your outage.",
    "estCustAffected": "19",
    "lastUpdateTime": "1609100041",
    "hazardFlag": "2",
    "latitude": "35.43509",
    "longitude": "-119.01444",
    "outageDevices": [
      {
        "latitude": "35.43209",
        "longitude": "-119.0142"
      },
      {
        "latitude": "35.43466",
        "longitude": "-119.01444"
      },
      {
        "latitude": "35.43218",
        "longitude": "-119.01477"
      }
    ],
    "regionName": "Oildale"
  },
  {
    "outageNumber": "1199499",
    "outageStartTime": "1609103875",
    "crewCurrentStatus": "PG&E has assigned a crew to assess the outage.",
    "autoEtor": "1609116300",
    "currentEtor": "1609116300",
    "cause": "Unknown - PG&E will be assessing the cause.",
    "estCustAffected": "1",
    "lastUpdateTime": "1609103880",
    "hazardFlag": "0",
    "latitude": "35.57674",
    "longitude": "-120.77862",
    "regionName": "Paso Robles"
  },
  {
    "outageNumber": "1199454",
    "outageStartTime": "1609096435",
    "crewCurrentStatus": "PG&E is assessing the cause at the outage location.",
    "autoEtor": "1609108200",
    "currentEtor": "1609108200",
    "cause": "PG&E is investigating the cause of your outage.",
    "estCustAffected": "1",
    "lastUpdateTime": "1609099870",
    "hazardFlag": "1",
    "latitude": "37.66149",
    "longitude": "-121.8737",
    "regionName": "Pleasanton"
  },
  {
    "outageNumber": "1193770",
    "outageStartTime": "1608318434",
    "crewCurrentStatus": "PG&E is sending a repair crew to the outage location.",
    "currentEtor": "1609117200",
    "cause": "Our preliminary determination is that your outage was caused by an equipment issue.",
    "estCustAffected": "1",
    "lastUpdateTime": "1608771104",
    "hazardFlag": "0",
    "latitude": "40.51659",
    "longitude": "-122.54527",
    "regionName": "Redding"
  },
  {
    "outageNumber": "1199364",
    "outageStartTime": "1609078177",
    "crewCurrentStatus": "PG&E is sending a repair crew to the outage location.",
    "currentEtor": "1609113720",
    "cause": "PG&E is investigating the cause of your outage.",
    "estCustAffected": "1",
    "lastUpdateTime": "1609103898",
    "hazardFlag": "0",
    "latitude": "37.4674",
    "longitude": "-122.23307",
    "regionName": "Redwood City"
  },
  {
    "outageNumber": "1199401",
    "outageStartTime": "1609089021",
    "crewEta": "1609107780",
    "crewCurrentStatus": "PG&E repair crew is en route to the outage location.",
    "currentEtor": "1609125420",
    "cause": "Our preliminary determination is that your outage was caused by an equipment issue.",
    "estCustAffected": "1",
    "lastUpdateTime": "1609100480",
    "hazardFlag": "0",
    "latitude": "36.5952",
    "longitude": "-121.44108",
    "regionName": "Salinas"
  },
  {
    "outageNumber": "1199447",
    "outageStartTime": "1609095169",
    "crewCurrentStatus": "PG&E is sending a repair crew to the outage location.",
    "currentEtor": "1609128000",
    "cause": "PG&E is investigating the cause of your outage.",
    "estCustAffected": "1",
    "lastUpdateTime": "1609097458",
    "hazardFlag": "1",
    "latitude": "37.61223",
    "longitude": "-122.43505",
    "regionName": "San Bruno"
  },
  {
    "outageNumber": "1199493",
    "outageStartTime": "1609102380",
    "crewCurrentStatus": "PG&E has assigned a crew to assess the outage.",
    "autoEtor": "1609113600",
    "currentEtor": "1609113600",
    "cause": "Unknown - PG&E will be assessing the cause.",
    "estCustAffected": "43",
    "lastUpdateTime": "1609102527",
    "hazardFlag": "0",
    "latitude": "37.80734",
    "longitude": "-122.42061",
    "outageDevices": [
      {
        "latitude": "37.80623",
        "longitude": "-122.42037"
      },
      {
        "latitude": "37.80801",
        "longitude": "-122.42046"
      },
      {
        "latitude": "37.80822",
        "longitude": "-122.42069"
      },
      {
        "latitude": "37.80738",
        "longitude": "-122.42074"
      }
    ],
    "regionName": "San Francisco"
  },
  {
    "outageNumber": "1199481",
    "outageStartTime": "1609099975",
    "crewCurrentStatus": "PG&E assessment crew is en route to the outage.",
    "autoEtor": "1609106400",
    "currentEtor": "1609106400",
    "cause": "Unknown - PG&E will be assessing the cause.",
    "estCustAffected": "1",
    "lastUpdateTime": "1609101121",
    "hazardFlag": "1",
    "latitude": "37.74274",
    "longitude": "-122.46666",
    "regionName": "San Francisco"
  },
  {
    "outageNumber": "1199456",
    "outageStartTime": "1609097040",
    "crewCurrentStatus": "PG&E is assessing the cause at the outage location.",
    "autoEtor": "1609108200",
    "currentEtor": "1609108200",
    "cause": "PG&E is investigating the cause of your outage.",
    "estCustAffected": "1",
    "lastUpdateTime": "1609103146",
    "hazardFlag": "0",
    "latitude": "37.31143",
    "longitude": "-121.78952",
    "regionName": "San Jose"
  },
  {
    "outageNumber": "1199484",
    "outageStartTime": "1609100330",
    "crewCurrentStatus": "PG&E has assigned a crew to assess the outage.",
    "autoEtor": "1609110900",
    "currentEtor": "1609110900",
    "cause": "Unknown - PG&E will be assessing the cause.",
    "estCustAffected": "1",
    "lastUpdateTime": "1609100393",
    "hazardFlag": "0",
    "latitude": "37.36957",
    "longitude": "-121.84553",
    "regionName": "San Jose"
  },
  {
    "outageNumber": "1199384",
    "outageStartTime": "1609085795",
    "crewCurrentStatus": "PG&E repair crew is on-site working to restore power.",
    "currentEtor": "1609117200",
    "cause": "Our preliminary determination is that your outage was caused by scheduled maintenance work.",
    "estCustAffected": "13",
    "lastUpdateTime": "1609086672",
    "hazardFlag": "0",
    "latitude": "38.54502",
    "longitude": "-122.72055",
    "outageDevices": [
      {
        "latitude": "38.5414",
        "longitude": "-122.71122"
      },
      {
        "latitude": "38.54585",
        "longitude": "-122.71134"
      },
      {
        "latitude": "38.54741",
        "longitude": "-122.7151"
      },
      {
        "latitude": "38.54848",
        "longitude": "-122.71998"
      },
      {
        "latitude": "38.54816",
        "longitude": "-122.72009"
      },
      {
        "latitude": "38.54592",
        "longitude": "-122.72045"
      },
      {
        "latitude": "38.54158",
        "longitude": "-122.71277"
      }
    ],
    "regionName": "Santa Rosa"
  },
  {
    "outageNumber": "1199498",
    "outageStartTime": "1609103107",
    "crewCurrentStatus": "PG&E assessment crew is en route to the outage.",
    "autoEtor": "1609113600",
    "currentEtor": "1609113600",
    "cause": "Unknown - PG&E will be assessing the cause.",
    "estCustAffected": "1",
    "lastUpdateTime": "1609103616",
    "hazardFlag": "1",
    "latitude": "37.95236",
    "longitude": "-121.25028",
    "regionName": "Stockton"
  },
  {
    "outageNumber": "1199502",
    "outageStartTime": "1609103580",
    "crewCurrentStatus": "PG&E has assigned a crew to assess the outage.",
    "autoEtor": "1609116300",
    "currentEtor": "1609116300",
    "cause": "Unknown - PG&E will be assessing the cause.",
    "estCustAffected": "997",
    "lastUpdateTime": "1609103967",
    "hazardFlag": "0",
    "latitude": "35.55814",
    "longitude": "-120.77718",
    "outageDevices": [
      {
        "latitude": "35.50849",
        "longitude": "-120.79768"
      },
      {
        "latitude": "35.51704",
        "longitude": "-120.78918"
      },
      {
        "latitude": "35.53427",
        "longitude": "-120.7753"
      },
      {
        "latitude": "35.53894",
        "longitude": "-120.77457"
      },
      {
        "latitude": "35.55604",
        "longitude": "-120.77549"
      },
      {
        "latitude": "35.57913",
        "longitude": "-120.79209"
      },
      {
        "latitude": "35.63322",
        "longitude": "-120.83772"
      },
      {
        "latitude": "35.73576",
        "longitude": "-120.93714"
      },
      {
        "latitude": "35.7493",
        "longitude": "-121.03756"
      },
      {
        "latitude": "35.74743",
        "longitude": "-121.04129"
      },
      {
        "latitude": "35.74638",
        "longitude": "-121.04097"
      },
      {
        "latitude": "35.66571",
        "longitude": "-120.99713"
      },
      {
        "latitude": "35.52702",
        "longitude": "-120.87459"
      },
      {
        "latitude": "35.51732",
        "longitude": "-120.86221"
      }
    ],
    "regionName": "Templeton"
  },
  {
    "outageNumber": "1199383",
    "outageStartTime": "1609085760",
    "crewCurrentStatus": "PG&E repair crew is on-site working to restore power.",
    "currentEtor": "1609120800",
    "cause": "Our preliminary determination is that your outage was caused by scheduled maintenance work.",
    "estCustAffected": "1",
    "lastUpdateTime": "1609087755",
    "hazardFlag": "0",
    "latitude": "37.70806",
    "longitude": "-121.53116",
    "regionName": "Tracy"
  },
  {
    "outageNumber": "1199496",
    "outageStartTime": "1609102573",
    "crewEta": "1609105260",
    "crewCurrentStatus": "PG&E is assessing the cause at the outage location.",
    "autoEtor": "1609115400",
    "currentEtor": "1609115400",
    "cause": "PG&E is investigating the cause of your outage.",
    "estCustAffected": "1",
    "lastUpdateTime": "1609103933",
    "hazardFlag": "1",
    "latitude": "39.17791",
    "longitude": "-123.1855",
    "regionName": "Ukiah"
  }
]